pomerge/__init__.py
pomerge/pomerge.py
pomerge-0.1.4.dist-info/METADATA
pomerge-0.1.4.dist-info/WHEEL
pomerge-0.1.4.dist-info/entry_points.txt
pomerge-0.1.4.dist-info/top_level.txt
pomerge-0.1.4.dist-info/RECORD
