Metadata-Version: 2.1
Name: pomerge
Version: 0.1.4
Summary: Merge known translations between .po files.
Home-page: https://github.com/JulienPalard/pomerge
Author: Julien Palard
Author-email: julien@palard.fr
License: MIT license
Keywords: pomerge
Platform: UNKNOWN
Classifier: Development Status :: 2 - Pre-Alpha
Classifier: Intended Audience :: Developers
Classifier: License :: OSI Approved :: MIT License
Classifier: Natural Language :: English
Classifier: Programming Language :: Python :: 3
Classifier: Programming Language :: Python :: 3.4
Classifier: Programming Language :: Python :: 3.5
Classifier: Programming Language :: Python :: 3.6
Requires-Dist: tqdm
Requires-Dist: polib
Provides-Extra: dev
Requires-Dist: pylint ; extra == 'dev'
Requires-Dist: flake8 ; extra == 'dev'
Requires-Dist: black ; extra == 'dev'
Requires-Dist: mypy ; extra == 'dev'
